fabrix/__init__.py
fabrix/console.py
fabrix/context.py
fabrix/evaluate.py
fabrix/exceptions.py
fabrix/functions/__init__.py
fabrix/functions/collections.py
fabrix/functions/conversions.py
fabrix/functions/dates.py
fabrix/functions/logical.py
fabrix/functions/maths.py
fabrix/functions/strings.py
fabrix/registry.py
fabrix/schemas.py
fabrix/utils.py
fabrix/validations.py
fabrix/version.py
fabrix-0.5.1.dist-info/LICENSE
fabrix-0.5.1.dist-info/METADATA
fabrix-0.5.1.dist-info/WHEEL
fabrix-0.5.1.dist-info/RECORD
