Metadata-Version: 2.3
Name: fabrix
Version: 0.5.1
Summary: A python toolkit to evaluate, validate, and debug Azure Data Factory & Microsoft Fabric pipeline expressions with rich tracing.
License: MIT
Author: Pit Nahrstedt
Author-email: pit.nahrstedt@outlook.de
Requires-Python: >=3.11,<4.0
Classifier: License :: OSI Approved :: MIT License
Classifier: Programming Language :: Python :: 3
Classifier: Programming Language :: Python :: 3.11
Classifier: Programming Language :: Python :: 3.12
Classifier: Programming Language :: Python :: 3.13
Requires-Dist: pydantic (>=2.11.7,<3.0.0)
Requires-Dist: python-dateutil (>=2.9.0.post0,<3.0.0)
Requires-Dist: pytz (>=2025.2,<2026.0)
Requires-Dist: rich (>=14.1.0,<15.0.0)
